odoo/addons/web_domain_field/README.rst
odoo/addons/web_domain_field/__init__.py
odoo/addons/web_domain_field/__manifest__.py
odoo/addons/web_domain_field/i18n/ca.po
odoo/addons/web_domain_field/i18n/es.po
odoo/addons/web_domain_field/i18n/web_domain_field.pot
odoo/addons/web_domain_field/static/description/icon.png
odoo/addons/web_domain_field/static/lib/js/pyeval.js
odoo/addons/web_domain_field/views/web_domain_field.xml
odoo13_addon_web_domain_field-13.0.1.0.1.dev7.dist-info/METADATA
odoo13_addon_web_domain_field-13.0.1.0.1.dev7.dist-info/WHEEL
odoo13_addon_web_domain_field-13.0.1.0.1.dev7.dist-info/top_level.txt
odoo13_addon_web_domain_field-13.0.1.0.1.dev7.dist-info/RECORD
